[
    {
        "date": "25-08-2025",
        "time": "08:00 - 16:00",
        "area": "KHU VỰC: một phẫn xã Tân Hưng tỉnh Đồng Nai"
    },
    {
        "date": "25-08-2025",
        "time": "08:00 - 16:00",
        "area": "KHU VỰC: một phẫn xã Tân Hưng tỉnh Đồng Nai"
    },
    {
        "date": "25-08-2025",
        "time": "08:00 - 16:00",
        "area": "KHU VỰC: một phẫn xã Tân Hưng tỉnh Đồng Nai"
    },
    {
        "date": "25-08-2025",
        "time": "08:00 - 16:00",
        "area": "KHU VỰC: một phẫn xã Tân Hưng tỉnh Đồng Nai"
    }
]